pydamage/__init__.py
pydamage/accuracy_model.py
pydamage/citation.py
pydamage/cli.py
pydamage/contig_stats.py
pydamage/damage.py
pydamage/exceptions.py
pydamage/filter.py
pydamage/gc_content.py
pydamage/likelihood_ratio.py
pydamage/main.py
pydamage/model_fit.py
pydamage/models.py
pydamage/optim.py
pydamage/parse_damage.py
pydamage/plot.py
pydamage/rescale.py
pydamage/utils.py
pydamage/vuong.py
pydamage-0.90.dist-info/LICENSE
pydamage-0.90.dist-info/METADATA
pydamage-0.90.dist-info/WHEEL
pydamage-0.90.dist-info/entry_points.txt
pydamage-0.90.dist-info/top_level.txt
pydamage-0.90.dist-info/RECORD
