Metadata-Version: 2.1
Name: pydamage
Version: 0.90
Summary: Damage parameter estimation for ancient DNA
Home-page: https://github.com/maxibor/pydamage
License: GNU-GPLv3
Requires-Python: >=3.10
License-File: LICENSE
Requires-Dist: click
Requires-Dist: numpy
Requires-Dist: pandas
Requires-Dist: pysam
Requires-Dist: scipy
Requires-Dist: statsmodels
Requires-Dist: matplotlib
Requires-Dist: tqdm
Requires-Dist: biopython
Requires-Dist: kneed
Requires-Dist: numba
